{
  "generated_at": "2026-04-07T18:13:02.999017-04:00",
  "event_key": "2026-04-07|La Suerte|Quiniela La Suerte 6PM",
  "target": {
    "time_rd": "2026-04-07 19:00",
    "lottery": "La Primera",
    "draw": "Quiniela La Primera Noche"
  },
  "best_play": {
    "time_rd": "2026-04-07 19:00",
    "lottery": "La Primera",
    "draw": "Quiniela La Primera Noche",
    "top12": [
      "21",
      "44",
      "63",
      "54",
      "26",
      "24",
      "30",
      "08",
      "03",
      "18",
      "14",
      "31"
    ],
    "topq": [
      "21",
      "44",
      "63"
    ],
    "pales": [
      "21-44",
      "21-63",
      "21-54"
    ],
    "fingerprint": "a55ed03cf101d4a0",
    "ok_alert": true,
    "best_signal": 0.02735165589853343,
    "best_a11": 4,
    "debug": {
      "best_signal_hist": 0.02735165589853343,
      "best_a11_hist": 4,
      "has_intraday_sources": 0,
      "intraday_events": 0,
      "today_observed_nums": 19,
      "source_pairs_today": 7,
      "source_rows_hist_used": 736
    }
  }
}