{
  "generated_at": "2026-03-31T14:11:52.437759-04:00",
  "event_key": "2026-03-31|Anguilla|Anguila 1PM",
  "target": {
    "time_rd": "2026-03-31 14:30",
    "lottery": "La Nacional",
    "draw": "Loteria Nacional- Gana Más"
  },
  "best_play": {
    "time_rd": "2026-03-31 14:30",
    "lottery": "La Nacional",
    "draw": "Loteria Nacional- Gana Más",
    "top12": [
      "36",
      "20",
      "40",
      "64",
      "89",
      "94",
      "41",
      "37",
      "95",
      "14",
      "13",
      "34"
    ],
    "topq": [
      "36",
      "20",
      "40"
    ],
    "pales": [
      "20-36",
      "36-40",
      "36-64"
    ],
    "fingerprint": "216a94b4cf13ee3d",
    "ok_alert": false,
    "best_signal": 0.000736309327687523,
    "best_a11": 5,
    "debug": {
      "best_signal_hist": 0.000736309327687523,
      "best_a11_hist": 5,
      "has_intraday_sources": 0,
      "intraday_events": 0,
      "today_observed_nums": 11,
      "source_pairs_today": 4,
      "source_rows_hist_used": 1270
    }
  }
}