{
  "generated_at": "2026-04-02T17:21:38.996054-04:00",
  "event_key": "2026-04-02|La Nacional|Loteria Nacional- Gana Más",
  "items": [
    {
      "generated_at": "2026-04-02T17:21:34.143711-04:00",
      "event_key": "2026-04-02|La Nacional|Loteria Nacional- Gana Más",
      "target": {
        "time_rd": "2026-04-02 18:00",
        "lottery": "Anguilla",
        "draw": "Anguila 6PM"
      },
      "best_play": {
        "time_rd": "2026-04-02 18:00",
        "lottery": "Anguilla",
        "draw": "Anguila 6PM",
        "top12": [
          "86",
          "16",
          "62",
          "46",
          "72",
          "03",
          "63",
          "66",
          "48",
          "59",
          "70",
          "54"
        ],
        "topq": [
          "86",
          "16",
          "62"
        ],
        "pales": [
          "16-86",
          "62-86",
          "46-86"
        ],
        "fingerprint": "0b1e384c92935ad1",
        "ok_alert": false,
        "best_signal": 0.003563880246052473,
        "best_a11": 6,
        "debug": {
          "best_signal_hist": 0.003563880246052473,
          "best_a11_hist": 6,
          "has_intraday_sources": 0,
          "intraday_events": 0,
          "today_observed_nums": 14,
          "source_pairs_today": 5,
          "source_rows_hist_used": 2460
        }
      }
    },
    {
      "generated_at": "2026-04-02T17:21:38.503729-04:00",
      "event_key": "2026-04-02|La Nacional|Loteria Nacional- Gana Más",
      "target": {
        "time_rd": "2026-04-02 18:00",
        "lottery": "La Suerte",
        "draw": "Quiniela La Suerte 6PM"
      },
      "best_play": {
        "time_rd": "2026-04-02 18:00",
        "lottery": "La Suerte",
        "draw": "Quiniela La Suerte 6PM",
        "top12": [
          "60",
          "64",
          "92",
          "66",
          "21",
          "07",
          "53",
          "88",
          "30",
          "87",
          "35",
          "02"
        ],
        "topq": [
          "60",
          "64",
          "92"
        ],
        "pales": [
          "60-64",
          "60-92",
          "60-66"
        ],
        "fingerprint": "d3c7f1015c93e1ff",
        "ok_alert": false,
        "best_signal": 0.003113038472448901,
        "best_a11": 10,
        "debug": {
          "best_signal_hist": 0.003113038472448901,
          "best_a11_hist": 10,
          "has_intraday_sources": 0,
          "intraday_events": 0,
          "today_observed_nums": 14,
          "source_pairs_today": 5,
          "source_rows_hist_used": 2460
        }
      }
    }
  ]
}