{
  "generated_at": "2026-06-28T16:14:43.167726-04:00",
  "event_key": "2026-06-28|La Nacional|Loteria Nacional- Gana Más",
  "target": {
    "time_rd": "2026-06-28 18:00",
    "lottery": "La Suerte",
    "draw": "Quiniela La Suerte 6PM"
  },
  "best_play": {
    "time_rd": "2026-06-28 18:00",
    "lottery": "La Suerte",
    "draw": "Quiniela La Suerte 6PM",
    "top12": [
      "38",
      "65",
      "27",
      "88",
      "92",
      "66",
      "53",
      "21",
      "73",
      "07",
      "30",
      "35"
    ],
    "topq": [
      "38",
      "65",
      "27"
    ],
    "pales": [
      "38-65",
      "27-38",
      "38-88"
    ],
    "fingerprint": "a2a084491cc26173",
    "ok_alert": false,
    "best_signal": 0.0027697553512929718,
    "best_a11": 9,
    "debug": {
      "best_signal_hist": 0.0027697553512929718,
      "best_a11_hist": 9,
      "has_intraday_sources": 0,
      "intraday_events": 0,
      "today_observed_nums": 14,
      "source_pairs_today": 5,
      "source_rows_hist_used": 2693
    }
  }
}