{
  "generated_at": "2026-05-19T19:16:51.110056-04:00",
  "event_key": "2026-05-19|La Primera|Quiniela La Primera Noche",
  "items": [
    {
      "generated_at": "2026-05-19T19:16:44.436499-04:00",
      "event_key": "2026-05-19|La Primera|Quiniela La Primera Noche",
      "target": {
        "time_rd": "2026-05-19 21:00",
        "lottery": "Anguilla",
        "draw": "Anguila 9PM"
      },
      "best_play": {
        "time_rd": "2026-05-19 21:00",
        "lottery": "Anguilla",
        "draw": "Anguila 9PM",
        "top12": [
          "40",
          "71",
          "13",
          "79",
          "10",
          "74",
          "68",
          "34",
          "48",
          "15",
          "76",
          "63"
        ],
        "topq": [
          "40",
          "71",
          "13"
        ],
        "pales": [
          "40-71",
          "13-40",
          "40-79"
        ],
        "fingerprint": "7346842a6ffb8de2",
        "ok_alert": false,
        "best_signal": 0.0061234590918285555,
        "best_a11": 3,
        "debug": {
          "best_signal_hist": 0.0061234590918285555,
          "best_a11_hist": 3,
          "has_intraday_sources": 0,
          "intraday_events": 0,
          "today_observed_nums": 22,
          "source_pairs_today": 8,
          "source_rows_hist_used": 947
        }
      }
    },
    {
      "generated_at": "2026-05-19T19:16:50.600739-04:00",
      "event_key": "2026-05-19|La Primera|Quiniela La Primera Noche",
      "target": {
        "time_rd": "2026-05-19 21:00",
        "lottery": "La Nacional",
        "draw": "Loteria Nacional- Noche"
      },
      "best_play": {
        "time_rd": "2026-05-19 21:00",
        "lottery": "La Nacional",
        "draw": "Loteria Nacional- Noche",
        "top12": [
          "56",
          "40",
          "13",
          "95",
          "93",
          "12",
          "38",
          "32",
          "68",
          "61",
          "11",
          "80"
        ],
        "topq": [
          "56",
          "40",
          "13"
        ],
        "pales": [
          "40-56",
          "13-56",
          "56-95"
        ],
        "fingerprint": "a51ec3ddb22c786e",
        "ok_alert": false,
        "best_signal": 0.007941902359447731,
        "best_a11": 3,
        "debug": {
          "best_signal_hist": 0.007941902359447731,
          "best_a11_hist": 3,
          "has_intraday_sources": 0,
          "intraday_events": 0,
          "today_observed_nums": 22,
          "source_pairs_today": 8,
          "source_rows_hist_used": 947
        }
      }
    }
  ]
}