{
  "generated_at": "2026-07-13T12:44:00.143127-04:00",
  "event_key": "2026-07-13|La Suerte|Quiniela La Suerte",
  "items": [
    {
      "generated_at": "2026-07-13T12:43:59.416778-04:00",
      "event_key": "2026-07-13|La Suerte|Quiniela La Suerte",
      "target": {
        "time_rd": "2026-07-13 13:00",
        "lottery": "Anguilla",
        "draw": "Anguila 1PM"
      },
      "best_play": {
        "time_rd": "2026-07-13 13:00",
        "lottery": "Anguilla",
        "draw": "Anguila 1PM",
        "top12": [
          "51",
          "53",
          "08",
          "37",
          "94",
          "77",
          "60",
          "33",
          "65",
          "81",
          "57",
          "89"
        ],
        "topq": [
          "51",
          "53",
          "08"
        ],
        "pales": [
          "51-53",
          "08-51",
          "37-51"
        ],
        "fingerprint": "5ef59a65f16decf6",
        "ok_alert": false,
        "best_signal": 0.0038451385599710354,
        "best_a11": 4,
        "debug": {
          "best_signal_hist": 0.0038451385599710354,
          "best_a11_hist": 4,
          "has_intraday_sources": 0,
          "intraday_events": 0,
          "today_observed_nums": 8,
          "source_pairs_today": 3,
          "source_rows_hist_used": 807
        }
      }
    }
  ]
}